d8s_nlp/__init__.py
d8s_nlp/nlp.py
tests/__init__.py
tests/test_nlp.py
d8s_nlp-0.2.0.dist-info/METADATA
d8s_nlp-0.2.0.dist-info/WHEEL
d8s_nlp-0.2.0.dist-info/top_level.txt
d8s_nlp-0.2.0.dist-info/zip-safe
d8s_nlp-0.2.0.dist-info/RECORD
