Metadata-Version: 2.1
Name: d8s-nlp
Version: 0.2.0
Summary: Democritus functions for working processing natural, human language.
Home-page: https://github.com/democritus-project/d8s-nlp
Author: Floyd Hightower
Author-email: floyd.hightower27@gmail.com
License: MIT license
Keywords: democritus,nlp,natural language processing
Platform: UNKNOWN
Classifier: Development Status :: 2 - Pre-Alpha
Classifier: Intended Audience :: Developers
Classifier: License :: OSI Approved :: MIT License
Classifier: Natural Language :: English
Classifier: Programming Language :: Python :: 3
Classifier: Programming Language :: Python :: 3.4
Classifier: Programming Language :: Python :: 3.5
Classifier: Programming Language :: Python :: 3.6
Classifier: Programming Language :: Python :: 3.7
Classifier: Programming Language :: Python :: 3.8
Classifier: Programming Language :: Python :: 3.9
Requires-Dist: matplotlib
Requires-Dist: numpy
Requires-Dist: textblob
Requires-Dist: wordcloud
Requires-Dist: nltk
Requires-Dist: d8s-math (==0.*)
Requires-Dist: d8s-lists (==0.*)
